MANIFEST.in
README.md
setup.cfg
setup.py
scrobbless/__init__.py
scrobbless/scrobbless.py
scrobbless/scrobbless_tester.py
scrobbless.egg-info/PKG-INFO
scrobbless.egg-info/SOURCES.txt
scrobbless.egg-info/dependency_links.txt
scrobbless.egg-info/not-zip-safe
scrobbless.egg-info/requires.txt
scrobbless.egg-info/top_level.txt