Metadata-Version: 1.0
Name: scrobbless
Version: 0.3.0
Summary: Minimal last.fm scrobbler
Home-page: http://github.com/sebojanko/scrobbless
Author: Sebastian Janko
Author-email: janko.sebastian@gmail.com
License: GNU GPL v3
Keywords: last.fm scrobbler
Platform: UNKNOWN
